kytchen_sdk/__init__.py
kytchen_sdk/client.py
kytchen_sdk/datasets.py
kytchen_sdk/errors.py
kytchen_sdk/keys.py
kytchen_sdk/types.py
kytchen_sdk-1.0.0.dist-info/METADATA
kytchen_sdk-1.0.0.dist-info/WHEEL
kytchen_sdk-1.0.0.dist-info/RECORD
