Metadata-Version: 2.4
Name: kytchen-sdk
Version: 1.0.0
Summary: Python SDK for Kytchen - BYOLLM Context Orchestration
Project-URL: Homepage, https://github.com/Shannon-Labs/Kytchen
Project-URL: Documentation, https://docs.kytchen.dev
Project-URL: Repository, https://github.com/Shannon-Labs/Kytchen
Author-email: Shannon Labs <hello@shannonlabs.ai>
License-Expression: MIT
Keywords: ai,context,llm,ml,orchestration
Classifier: Development Status :: 4 - Beta
Classifier: Intended Audience :: Developers
Classifier: License :: OSI Approved :: MIT License
Classifier: Programming Language :: Python :: 3
Classifier: Programming Language :: Python :: 3.9
Classifier: Programming Language :: Python :: 3.10
Classifier: Programming Language :: Python :: 3.11
Classifier: Programming Language :: Python :: 3.12
Classifier: Topic :: Scientific/Engineering :: Artificial Intelligence
Requires-Python: >=3.9
Requires-Dist: httpx>=0.25.0
Requires-Dist: pydantic>=2.0.0
Provides-Extra: async
Requires-Dist: httpx[http2]>=0.25.0; extra == 'async'
Provides-Extra: dev
Requires-Dist: pytest-asyncio>=0.21.0; extra == 'dev'
Requires-Dist: pytest>=7.0.0; extra == 'dev'
Requires-Dist: ruff>=0.1.0; extra == 'dev'
